{
  "metadata": {
    "name": "Demographics.xlsx_flow",
    "description": "",
    "asset_type": "data_flow",
    "origin_country": "us",
    "asset_category": "USER",
    "created_at": "2023-10-24T12:42:49Z",
    "created": 1698151369504,
    "asset_id": "data_flow.Demographicsxlsxflow",
    "asset_attributes": [
      "data_flow"
    ]
  },
  "entity": {
    "data_flow": {
      "_entity_only": false
    }
  },
  "attachments": [
    {
      "asset_type": "data_flow",
      "description": "",
      "name": "data_flow",
      "mime": "application/json",
      "object_key": "data_flow/Demographics.xlsx_flow",
      "is_referenced": true,
      "is_managed": false,
      "user_data": {},
      "is_partitioned": false,
      "object_key_is_read_only": false,
      "created_at": "2023-10-24T12:42:49Z",
      "id": "575b1322-1bd9-43b5-b4a4-b2a91a38717c",
      "is_remote": false
    }
  ]
}